{
  "caseID" : "case-c8113e0835855f79ca1750b8",
  "commitHash" : "72c643eab2f289d5b6625ae80bac28c3350b680e",
  "commitMessage" : "Update pod RxSwift, RxCocoa to 4.5.0\n",
  "commitURL" : "https://github.com/shadowsocks/ShadowsocksX-NG/commit/72c643eab2f289d5b6625ae80bac28c3350b680e",
  "durationSeconds" : 58.363232016563416,
  "entityNames" : [
    "(() -> Void)?",
    "onSubscribe"
  ],
  "rawRefactoring" : {
    "category" : "basic",
    "current_content" : {
      "attributes" : [

      ],
      "data_type" : {
        "is_optional" : true,
        "name" : "(() -> Void)?"
      },
      "is_variadic" : false,
      "location_info" : {
        "file_path" : "Pods/RxSwift/RxSwift/Observables/Do.swift",
        "location" : {
          "end_position" : 3111,
          "start_position" : 3083
        }
      },
      "modifiers" : [

      ],
      "name" : "onSubscribe",
      "order" : 2
    },
    "type" : "Add Parameter Refactoring"
  },
  "refactoringIndex" : 1217,
  "refactoringType" : "Add Parameter Refactoring",
  "repoID" : "shadowsocks-shadowsocksx-ng",
  "repoName" : "shadowsocks/ShadowsocksX-NG",
  "repoURL" : "https://github.com/shadowsocks/ShadowsocksX-NG.git",
  "runID" : "app-batch",
  "swiftPaths" : [
    "Pods/RxSwift/RxSwift/Observables/Do.swift"
  ]
}