{
  "caseID" : "case-79ab0cccda54dfa76f041ae4",
  "commitHash" : "61fe7d2b81681bb3cd4b77e886761b1875a611f0",
  "commitMessage" : "feat: added an option that preserve the menu bar items position when toggle `Combined modules`\n",
  "commitURL" : "https://github.com/exelban/stats/commit/61fe7d2b81681bb3cd4b77e886761b1875a611f0",
  "durationSeconds" : 3.3481370210647583,
  "entityNames" : [
    "init"
  ],
  "rawRefactoring" : {
    "category" : "basic",
    "old_content" : {
      "additional_trailing_closures" : [

      ],
      "arguments" : [
        {
          "value" : "PreferencesSection([\n            PreferencesRow(localizedString(\"macOS widgets\"), component: switchView(\n                action: #selector(self.toggleSystemWidgetsUpdatesState),\n                state: self.systemWidgetsUpdatesState\n            ))\n        ])"
        }
      ],
      "call" : "addArrangedSubview",
      "has_self_reference" : false,
      "internal_inline_calls" : [

      ],
      "location_info" : {
        "file_path" : "Stats/Views/AppSettings.swift",
        "location" : {
          "end_position" : 4951,
          "start_position" : 4635
        }
      }
    },
    "parent" : {
      "attributes" : [

      ],
      "functions" : [

      ],
      "location_info" : {
        "file_path" : "Stats/Views/AppSettings.swift",
        "location" : {
          "end_position" : 10262,
          "start_position" : 2859
        }
      },
      "modifiers" : [

      ],
      "name" : "init",
      "parameters" : [

      ]
    },
    "type" : "Remove statement refactoring"
  },
  "refactoringIndex" : 8,
  "refactoringType" : "Remove statement refactoring",
  "repoID" : "exelban-stats",
  "repoName" : "exelban/stats",
  "repoURL" : "https://github.com/exelban/stats.git",
  "runID" : "app-batch",
  "swiftPaths" : [
    "Stats/Views/AppSettings.swift"
  ]
}