{
  "caseID": "case-256d75f1da5b1b25889efe6f",
  "commitHash": "c5c8bf1b3c22d3302ab395d8b6f588d59ad76ceb",
  "commitMessage": "DDC support for high-end M2 (Pro/Max/Ultra) systems (#1404)\n\n",
  "commitURL": "https://github.com/MonitorControl/MonitorControl/commit/c5c8bf1b3c22d3302ab395d8b6f588d59ad76ceb",
  "durationSeconds": 4.021359086036682,
  "entityNames": [
    "inout IOregService",
    "io_service_t",
    "ioregService",
    "service",
    "setIORegServiceDCPAVServiceProxy"
  ],
  "rawRefactoring": {
    "category": "basic",
    "old_content": "private",
    "parent": {
      "attributes": [],
      "body": {
        "content": "if let unmanagedLocation = IORegistryEntryCreateCFProperty(service, \"Location\" as CFString, kCFAllocatorDefault, IOOptionBits(kIORegistryIterateRecursively)), let location = unmanagedLocation.takeRetainedValue() as? String {\n      ioregService.location = location\n      if location == \"External\" {\n        ioregService.service = IOAVServiceCreateWithService(kCFAllocatorDefault, service)?.takeRetainedValue() as IOAVService\n      }\n    }"
      },
      "location_info": {
        "file_path": "MonitorControl/Support/Arm64DDC.swift",
        "location": {
          "end_position": 11836,
          "start_position": 11129,
          "start_line": 225,
          "end_line": 235
        }
      },
      "modifiers": [
        "private",
        "static"
      ],
      "name": "setIORegServiceDCPAVServiceProxy",
      "parameters": [
        {
          "attributes": [],
          "data_type": {
            "is_optional": false,
            "name": "io_service_t"
          },
          "is_variadic": false,
          "location_info": {
            "file_path": "MonitorControl/Support/Arm64DDC.swift",
            "location": {
              "end_position": 11355,
              "start_position": 11332,
              "start_line": 228,
              "end_line": 228
            }
          },
          "modifiers": [],
          "name": "service",
          "order": 0
        },
        {
          "attributes": [],
          "data_type": {
            "is_optional": false,
            "name": "inout IOregService"
          },
          "is_variadic": false,
          "location_info": {
            "file_path": "MonitorControl/Support/Arm64DDC.swift",
            "location": {
              "end_position": 11387,
              "start_position": 11355,
              "start_line": 228,
              "end_line": 228
            }
          },
          "modifiers": [],
          "name": "ioregService",
          "order": 1
        }
      ]
    },
    "type": "Remove modifier refactoring"
  },
  "refactoringIndex": 70,
  "refactoringType": "Remove modifier refactoring",
  "repoID": "monitorcontrol-monitorcontrol",
  "repoName": "MonitorControl/MonitorControl",
  "repoURL": "https://github.com/MonitorControl/MonitorControl.git",
  "runID": "app-batch",
  "swiftPaths": [
    "MonitorControl/Support/Arm64DDC.swift"
  ]
}
