{
  "caseID": "case-d4fb3eec9c2bc580f330868c",
  "commitHash": "184bf068b77ae1790c645a2569a2554020dbca8b",
  "commitMessage": "update outdated pods\n",
  "commitURL": "https://github.com/shadowsocks/ShadowsocksX-NG/commit/184bf068b77ae1790c645a2569a2554020dbca8b",
  "durationSeconds": 1072.566666007042,
  "entityNames": [
    "Data?",
    "HTTPURLResponse",
    "S",
    "ValidationResult",
    "acceptableContentTypes",
    "data",
    "guard",
    "response"
  ],
  "rawRefactoring": {
    "category": "basic",
    "current_content": {
      "conditions": [
        {
          "condition_value": {
            "optional_binding": {
              "_0": {
                "description": "let data = data",
                "initializer_clause": {
                  "has_self_reference": false,
                  "value": {
                    "reference": {
                      "arguments": [],
                      "name": "data"
                    }
                  }
                },
                "is_binding_self": false,
                "is_in_out": false,
                "is_let": true,
                "is_var": false,
                "name": "data"
              }
            }
          },
          "location_info": {
            "file_path": "Pods/Alamofire/Source/Validation.swift",
            "location": {
              "end_position": 3678,
              "start_position": 3661,
              "start_line": 100,
              "end_line": 100
            }
          }
        },
        {
          "condition_value": {
            "boolean_expr": {
              "_0": "!data.isEmpty"
            }
          },
          "location_info": {
            "file_path": "Pods/Alamofire/Source/Validation.swift",
            "location": {
              "end_position": 3692,
              "start_position": 3678,
              "start_line": 100,
              "end_line": 100
            }
          }
        }
      ],
      "location_info": {
        "file_path": "Pods/Alamofire/Source/Validation.swift",
        "location": {
          "end_position": 3720,
          "start_position": 3646,
          "start_line": 99,
          "end_line": 100
        }
      },
      "name": "guard"
    },
    "parent": {
      "attributes": [],
      "body": {
        "content": "guard let data = data, !data.isEmpty else { return .success(()) }\n\n        return validate(contentType: acceptableContentTypes, response: response)"
      },
      "generic_clause": "<S: Sequence>",
      "location_info": {
        "file_path": "Pods/Alamofire/Source/Validation.swift",
        "location": {
          "end_position": 3808,
          "start_position": 3337,
          "start_line": 91,
          "end_line": 103
        }
      },
      "modifiers": [
        "fileprivate"
      ],
      "name": "validate",
      "parameters": [
        {
          "attributes": [],
          "data_type": {
            "is_optional": false,
            "name": "S"
          },
          "is_variadic": false,
          "label": "contentType",
          "location_info": {
            "file_path": "Pods/Alamofire/Source/Validation.swift",
            "location": {
              "end_position": 3447,
              "start_position": 3409,
              "start_line": 95,
              "end_line": 95
            }
          },
          "modifiers": [],
          "name": "acceptableContentTypes",
          "order": 0
        },
        {
          "attributes": [],
          "data_type": {
            "is_optional": false,
            "name": "HTTPURLResponse"
          },
          "is_variadic": false,
          "location_info": {
            "file_path": "Pods/Alamofire/Source/Validation.swift",
            "location": {
              "end_position": 3517,
              "start_position": 3447,
              "start_line": 95,
              "end_line": 96
            }
          },
          "modifiers": [],
          "name": "response",
          "order": 1
        },
        {
          "attributes": [],
          "data_type": {
            "is_optional": true,
            "name": "Data?"
          },
          "is_variadic": false,
          "location_info": {
            "file_path": "Pods/Alamofire/Source/Validation.swift",
            "location": {
              "end_position": 3572,
              "start_position": 3517,
              "start_line": 96,
              "end_line": 97
            }
          },
          "modifiers": [],
          "name": "data",
          "order": 2
        }
      ],
      "return_clause": {
        "data_type": {
          "is_optional": false,
          "name": "ValidationResult"
        },
        "description": "-> ValidationResult"
      },
      "where_clause": "where S.Iterator.Element == String"
    },
    "type": "Add statement refactoring"
  },
  "refactoringIndex": 1120,
  "refactoringType": "Add statement refactoring",
  "repoID": "shadowsocks-shadowsocksx-ng",
  "repoName": "shadowsocks/ShadowsocksX-NG",
  "repoURL": "https://github.com/shadowsocks/ShadowsocksX-NG.git",
  "runID": "app-batch",
  "swiftPaths": [
    "Pods/Alamofire/Source/Validation.swift"
  ]
}
