{
  "caseID" : "case-90316804768965ecdb4fb365",
  "commitHash" : "72c643eab2f289d5b6625ae80bac28c3350b680e",
  "commitMessage" : "Update pod RxSwift, RxCocoa to 4.5.0\n",
  "commitURL" : "https://github.com/shadowsocks/ShadowsocksX-NG/commit/72c643eab2f289d5b6625ae80bac28c3350b680e",
  "durationSeconds" : 58.363232016563416,
  "entityNames" : [
    "@escaping (@escaping SingleObserver) -> Disposable",
    "Single<ElementType>",
    "create",
    "subscribe"
  ],
  "rawRefactoring" : {
    "category" : "basic",
    "current_content" : "static",
    "parent" : {
      "attributes" : [

      ],
      "body" : {
        "content" : "let source = Observable<ElementType>.create { observer in\n            return subscribe { event in\n                switch event {\n                case .success(let element):\n                    observer.on(.next(element))\n                    observer.on(.completed)\n                case .error(let error):\n                    observer.on(.error(error))\n                }\n            }\n        }\n        \n        return PrimitiveSequence(raw: source)"
      },
      "location_info" : {
        "file_path" : "Pods/RxSwift/RxSwift/Traits/Single.swift",
        "location" : {
          "end_position" : 1845,
          "start_position" : 834
        }
      },
      "modifiers" : [
        "public",
        "static"
      ],
      "name" : "create",
      "parameters" : [
        {
          "attributes" : [
            {
              "annotation" : {
                "escaping" : {

                }
              },
              "arguments" : [

              ]
            },
            {
              "annotation" : {
                "escaping" : {

                }
              },
              "arguments" : [

              ]
            }
          ],
          "data_type" : {
            "is_optional" : false,
            "name" : "@escaping (@escaping SingleObserver) -> Disposable"
          },
          "is_variadic" : false,
          "location_info" : {
            "file_path" : "Pods/RxSwift/RxSwift/Traits/Single.swift",
            "location" : {
              "end_position" : 1356,
              "start_position" : 1295
            }
          },
          "modifiers" : [

          ],
          "name" : "subscribe",
          "order" : 0
        }
      ],
      "return_clause" : {
        "data_type" : {
          "is_optional" : false,
          "name" : "Single<ElementType>"
        },
        "description" : "-> Single<ElementType>"
      }
    },
    "type" : "Add modifier refactoring"
  },
  "refactoringIndex" : 2641,
  "refactoringType" : "Add modifier refactoring",
  "repoID" : "shadowsocks-shadowsocksx-ng",
  "repoName" : "shadowsocks/ShadowsocksX-NG",
  "repoURL" : "https://github.com/shadowsocks/ShadowsocksX-NG.git",
  "runID" : "app-batch",
  "swiftPaths" : [
    "Pods/RxSwift/RxSwift/Traits/Single.swift"
  ]
}