{
  "caseID" : "case-5a33a0dfa8729a4859783196",
  "commitHash" : "7500a8ec2bb20a1e96d4fc6e18e5a88f23091807",
  "commitMessage" : "Swift 6 Native Builds (#3880)\n\n### Goals :soccer:\r\nThis PR tracks the implementation of full concurrency checking when\r\nbuilding in Swift 6 mode. It's unknown whether all of these changes will\r\nbe fully backward compatible.\r\n\r\n### Implementation Details :construction:\r\nThis PR largely consists of `Sendable` annotations, with a few logic\r\nchanges to fix actual safety issues.\r\n\r\n### Testing Details :mag:\r\nTests updated with needed annotations, but mutation warnings need a\r\nlarger overall refactor.",
  "commitURL" : "https://github.com/Alamofire/Alamofire/commit/7500a8ec2bb20a1e96d4fc6e18e5a88f23091807",
  "durationSeconds" : 73.471343994140625,
  "entityNames" : [
    "MultipartEncodingFailureReason",
    "Sendable",
    "URL",
    "any Error",
    "at",
    "atURL",
    "bodyPartFileIsDirectory",
    "bodyPartFileNotReachable"
  ],
  "rawRefactoring" : {
    "category" : "basic",
    "current_content" : {
      "name" : "Sendable"
    },
    "parent" : {
      "attributes" : [

      ],
      "cases" : [
        {
          "attributes" : [

          ],
          "location_info" : {
            "file_path" : "Source/Core/AFError.swift",
            "location" : {
              "end_position" : 1736,
              "start_position" : 1604
            }
          },
          "modifiers" : [

          ],
          "name" : "bodyPartURLInvalid",
          "parameters" : [
            {
              "attributes" : [

              ],
              "data_type" : {
                "is_optional" : false,
                "name" : "URL"
              },
              "is_variadic" : false,
              "location_info" : {
                "file_path" : "Source/Core/AFError.swift",
                "location" : {
                  "end_position" : 1735,
                  "start_position" : 1727
                }
              },
              "modifiers" : [

              ],
              "name" : "url",
              "order" : 0
            }
          ]
        },
        {
          "attributes" : [

          ],
          "location_info" : {
            "file_path" : "Source/Core/AFError.swift",
            "location" : {
              "end_position" : 1893,
              "start_position" : 1736
            }
          },
          "modifiers" : [

          ],
          "name" : "bodyPartFilenameInvalid",
          "parameters" : [
            {
              "attributes" : [

              ],
              "data_type" : {
                "is_optional" : false,
                "name" : "URL"
              },
              "is_variadic" : false,
              "location_info" : {
                "file_path" : "Source/Core/AFError.swift",
                "location" : {
                  "end_position" : 1892,
                  "start_position" : 1885
                }
              },
              "modifiers" : [

              ],
              "name" : "in",
              "order" : 0
            }
          ]
        },
        {
          "attributes" : [

          ],
          "location_info" : {
            "file_path" : "Source/Core/AFError.swift",
            "location" : {
              "end_position" : 2006,
              "start_position" : 1893
            }
          },
          "modifiers" : [

          ],
          "name" : "bodyPartFileNotReachable",
          "parameters" : [
            {
              "attributes" : [

              ],
              "data_type" : {
                "is_optional" : false,
                "name" : "URL"
              },
              "is_variadic" : false,
              "location_info" : {
                "file_path" : "Source/Core/AFError.swift",
                "location" : {
                  "end_position" : 2005,
                  "start_position" : 1998
                }
              },
              "modifiers" : [

              ],
              "name" : "at",
              "order" : 0
            }
          ]
        },
        {
          "attributes" : [

          ],
          "location_info" : {
            "file_path" : "Source/Core/AFError.swift",
            "location" : {
              "end_position" : 2174,
              "start_position" : 2006
            }
          },
          "modifiers" : [

          ],
          "name" : "bodyPartFileNotReachableWithError",
          "parameters" : [
            {
              "attributes" : [

              ],
              "data_type" : {
                "is_optional" : false,
                "name" : "URL"
              },
              "is_variadic" : false,
              "location_info" : {
                "file_path" : "Source/Core/AFError.swift",
                "location" : {
                  "end_position" : 2157,
                  "start_position" : 2145
                }
              },
              "modifiers" : [

              ],
              "name" : "atURL",
              "order" : 0
            },
            {
              "attributes" : [

              ],
              "data_type" : {
                "is_optional" : false,
                "name" : "any Error"
              },
              "is_variadic" : false,
              "location_info" : {
                "file_path" : "Source/Core/AFError.swift",
                "location" : {
                  "end_position" : 2173,
                  "start_position" : 2157
                }
              },
              "modifiers" : [

              ],
              "name" : "error",
              "order" : 1
            }
          ]
        },
        {
          "attributes" : [

          ],
          "location_info" : {
            "file_path" : "Source/Core/AFError.swift",
            "location" : {
              "end_position" : 2292,
              "start_position" : 2174
            }
          },
          "modifiers" : [

          ],
          "name" : "bodyPartFileIsDirectory",
          "parameters" : [
            {
              "attributes" : [

              ],
              "data_type" : {
                "is_optional" : false,
                "name" : "URL"
              },
              "is_variadic" : false,
              "location_info" : {
                "file_path" : "Source/Core/AFError.swift",
                "location" : {
                  "end_position" : 2291,
                  "start_position" : 2284
                }
              },
              "modifiers" : [

              ],
              "name" : "at",
              "order" : 0
            }
          ]
        },
        {
          "attributes" : [

          ],
          "location_info" : {
            "file_path" : "Source/Core/AFError.swift",
            "location" : {
              "end_position" : 2434,
              "start_position" : 2292
            }
          },
          "modifiers" : [

          ],
          "name" : "bodyPartFileSizeNotAvailable",
          "parameters" : [
            {
              "attributes" : [

              ],
              "data_type" : {
                "is_optional" : false,
                "name" : "URL"
              },
              "is_variadic" : false,
              "location_info" : {
                "file_path" : "Source/Core/AFError.swift",
                "location" : {
                  "end_position" : 2433,
                  "start_position" : 2426
                }
              },
              "modifiers" : [

              ],
              "name" : "at",
              "order" : 0
            }
          ]
        },
        {
          "attributes" : [

          ],
          "location_info" : {
            "file_path" : "Source/Core/AFError.swift",
            "location" : {
              "end_position" : 2610,
              "start_position" : 2434
            }
          },
          "modifiers" : [

          ],
          "name" : "bodyPartFileSizeQueryFailedWithError",
          "parameters" : [
            {
              "attributes" : [

              ],
              "data_type" : {
                "is_optional" : false,
                "name" : "URL"
              },
              "is_variadic" : false,
              "location_info" : {
                "file_path" : "Source/Core/AFError.swift",
                "location" : {
                  "end_position" : 2593,
                  "start_position" : 2580
                }
              },
              "modifiers" : [

              ],
              "name" : "forURL",
              "order" : 0
            },
            {
              "attributes" : [

              ],
              "data_type" : {
                "is_optional" : false,
                "name" : "any Error"
              },
              "is_variadic" : false,
              "location_info" : {
                "file_path" : "Source/Core/AFError.swift",
                "location" : {
                  "end_position" : 2609,
                  "start_position" : 2593
                }
              },
              "modifiers" : [

              ],
              "name" : "error",
              "order" : 1
            }
          ]
        },
        {
          "attributes" : [

          ],
          "location_info" : {
            "file_path" : "Source/Core/AFError.swift",
            "location" : {
              "end_position" : 2745,
              "start_position" : 2610
            }
          },
          "modifiers" : [

          ],
          "name" : "bodyPartInputStreamCreationFailed",
          "parameters" : [
            {
              "attributes" : [

              ],
              "data_type" : {
                "is_optional" : false,
                "name" : "URL"
              },
              "is_variadic" : false,
              "location_info" : {
                "file_path" : "Source/Core/AFError.swift",
                "location" : {
                  "end_position" : 2744,
                  "start_position" : 2736
                }
              },
              "modifiers" : [

              ],
              "name" : "for",
              "order" : 0
            }
          ]
        },
        {
          "attributes" : [

          ],
          "location_info" : {
            "file_path" : "Source/Core/AFError.swift",
            "location" : {
              "end_position" : 2897,
              "start_position" : 2745
            }
          },
          "modifiers" : [

          ],
          "name" : "outputStreamCreationFailed",
          "parameters" : [
            {
              "attributes" : [

              ],
              "data_type" : {
                "is_optional" : false,
                "name" : "URL"
              },
              "is_variadic" : false,
              "location_info" : {
                "file_path" : "Source/Core/AFError.swift",
                "location" : {
                  "end_position" : 2896,
                  "start_position" : 2888
                }
              },
              "modifiers" : [

              ],
              "name" : "for",
              "order" : 0
            }
          ]
        },
        {
          "attributes" : [

          ],
          "location_info" : {
            "file_path" : "Source/Core/AFError.swift",
            "location" : {
              "end_position" : 3069,
              "start_position" : 2897
            }
          },
          "modifiers" : [

          ],
          "name" : "outputStreamFileAlreadyExists",
          "parameters" : [
            {
              "attributes" : [

              ],
              "data_type" : {
                "is_optional" : false,
                "name" : "URL"
              },
              "is_variadic" : false,
              "location_info" : {
                "file_path" : "Source/Core/AFError.swift",
                "location" : {
                  "end_position" : 3068,
                  "start_position" : 3061
                }
              },
              "modifiers" : [

              ],
              "name" : "at",
              "order" : 0
            }
          ]
        },
        {
          "attributes" : [

          ],
          "location_info" : {
            "file_path" : "Source/Core/AFError.swift",
            "location" : {
              "end_position" : 3213,
              "start_position" : 3069
            }
          },
          "modifiers" : [

          ],
          "name" : "outputStreamURLInvalid",
          "parameters" : [
            {
              "attributes" : [

              ],
              "data_type" : {
                "is_optional" : false,
                "name" : "URL"
              },
              "is_variadic" : false,
              "location_info" : {
                "file_path" : "Source/Core/AFError.swift",
                "location" : {
                  "end_position" : 3212,
                  "start_position" : 3204
                }
              },
              "modifiers" : [

              ],
              "name" : "url",
              "order" : 0
            }
          ]
        },
        {
          "attributes" : [

          ],
          "location_info" : {
            "file_path" : "Source/Core/AFError.swift",
            "location" : {
              "end_position" : 3364,
              "start_position" : 3213
            }
          },
          "modifiers" : [

          ],
          "name" : "outputStreamWriteFailed",
          "parameters" : [
            {
              "attributes" : [

              ],
              "data_type" : {
                "is_optional" : false,
                "name" : "any Error"
              },
              "is_variadic" : false,
              "location_info" : {
                "file_path" : "Source/Core/AFError.swift",
                "location" : {
                  "end_position" : 3363,
                  "start_position" : 3347
                }
              },
              "modifiers" : [

              ],
              "name" : "error",
              "order" : 0
            }
          ]
        },
        {
          "attributes" : [

          ],
          "location_info" : {
            "file_path" : "Source/Core/AFError.swift",
            "location" : {
              "end_position" : 3521,
              "start_position" : 3364
            }
          },
          "modifiers" : [

          ],
          "name" : "inputStreamReadFailed",
          "parameters" : [
            {
              "attributes" : [

              ],
              "data_type" : {
                "is_optional" : false,
                "name" : "any Error"
              },
              "is_variadic" : false,
              "location_info" : {
                "file_path" : "Source/Core/AFError.swift",
                "location" : {
                  "end_position" : 3520,
                  "start_position" : 3504
                }
              },
              "modifiers" : [

              ],
              "name" : "error",
              "order" : 0
            }
          ]
        }
      ],
      "classes" : [

      ],
      "conformed_types" : [
        {
          "name" : "Sendable"
        }
      ],
      "enums" : [

      ],
      "functions" : [

      ],
      "initializers" : [

      ],
      "location_info" : {
        "file_path" : "Source/Core/AFError.swift",
        "location" : {
          "end_position" : 3527,
          "start_position" : 1468
        }
      },
      "modifiers" : [
        "public"
      ],
      "name" : "MultipartEncodingFailureReason",
      "protocols" : [

      ],
      "structs" : [

      ],
      "subscripts" : [

      ],
      "type_aliases" : [

      ],
      "variables" : [

      ]
    },
    "type" : "Add Confromed Type Refactoring"
  },
  "refactoringIndex" : 36,
  "refactoringType" : "Add Confromed Type Refactoring",
  "repoID" : "alamofire-alamofire",
  "repoName" : "Alamofire/Alamofire",
  "repoURL" : "https://github.com/Alamofire/Alamofire.git",
  "runID" : "app-batch",
  "swiftPaths" : [
    "Source/Core/AFError.swift"
  ]
}